titr/__init__.py
titr/config.py
titr/database.py
titr/datum_console.py
titr/helper.py
titr/outlook.py
titr/titr_main.py
titr-0.10.0.dist-info/LICENSE
titr-0.10.0.dist-info/METADATA
titr-0.10.0.dist-info/WHEEL
titr-0.10.0.dist-info/entry_points.txt
titr-0.10.0.dist-info/top_level.txt
titr-0.10.0.dist-info/RECORD
