Metadata-Version: 2.1
Name: titr
Version: 0.10.0
Summary: A CLI for time tracking
Home-page: https://github.com/blairfrandeen/titr
Author: Blair Frandeen
Author-email: blairfrandeen@gmail.com
Project-URL: Bug Tracker, https://github.com/blairfrandeen/titr/issues
Classifier: Programming Language :: Python :: 3
Classifier: License :: OSI Approved :: MIT License
Classifier: Operating System :: OS Independent
Requires-Python: >=3.10
License-File: LICENSE
Requires-Dist: click
Requires-Dist: colorama
Requires-Dist: pandas
Requires-Dist: pyperclip
Requires-Dist: pywin32 ; platform_system == "Windows"
